{
  "419286": [
    {
      "fileName": "!mixinbooter-4.2.jar",
      "staged": false,
      "deleted": false,
      "md5": "QI0OC+kk8svFtHNcFF+1Yg==",
      "fileId": 3687785
    }
  ],
  "485908": [
    {
      "fileName": "1.0.2\u002BRawOres\u002B1.12.2.jar",
      "staged": false,
      "deleted": false,
      "md5": "X8BkgMOx876mSKH4To1x3w==",
      "fileId": 3396480
    }
  ],
  "304493": [
    {
      "fileName": "alcatrazcore-1.0.4.jar",
      "staged": false,
      "deleted": false,
      "md5": "5ks6vc+tyeT4lUh+L6fYIg==",
      "fileId": 2666560
    }
  ],
  "320093": [
    {
      "fileName": "anvilpatch-1.1.1.jar",
      "staged": false,
      "deleted": false,
      "md5": "TlJ8YHx3xCl/YqGwPJHJSg==",
      "fileId": 3602349
    }
  ],
  "224472": [
    {
      "fileName": "AppleCore-mc1.12.2-3.4.0.jar",
      "staged": false,
      "deleted": false,
      "md5": "qN1jWoH+1Zvg0YIG/Tg/bg==",
      "fileId": 2969118
    }
  ],
  "248787": [
    {
      "fileName": "AppleSkin-mc1.12-1.0.14.jar",
      "staged": false,
      "deleted": false,
      "md5": "tDWGDVz6I7xT07jhIL6R1A==",
      "fileId": 2987247
    }
  ],
  "321792": [
    {
      "fileName": "AquaAcrobatics-1.12.2.jar",
      "staged": false,
      "deleted": false,
      "md5": "K+PwEhMKbXTV9RJtNq2N7A==",
      "fileId": 3705989
    }
  ],
  "377088": [
    {
      "fileName": "armorcurve-1.2.9.jar",
      "staged": false,
      "deleted": false,
      "md5": "DZvsfqO2+1ptdgn/yiNFgA==",
      "fileId": 2972692
    }
  ],
  "364982": [
    {
      "fileName": "ASMC-1.12.2-1.0.2.jar",
      "staged": false,
      "deleted": false,
      "md5": "RKGl0U/UamalSc7SlEO79g==",
      "fileId": 2902440
    }
  ],
  "280510": [
    {
      "fileName": "AttributeFix-1.12.2-1.0.10.jar",
      "staged": false,
      "deleted": false,
      "md5": "to2fzNwABeJwpbLKpF+BaQ==",
      "fileId": 2810157
    }
  ],
  "250363": [
    {
      "fileName": "AutoRegLib-1.3-32.jar",
      "staged": false,
      "deleted": false,
      "md5": "TlpLiBwnseRQKpoWwAiCrQ==",
      "fileId": 2746011
    }
  ],
  "0": [
    {
      "fileName": "backstab-1.12.2-1.0.3.2-fix.jar",
      "staged": true,
      "deleted": false,
      "md5": "04H4Ie+2dFJuTiOqIlesnw==",
      "fileId": 0
    },
    {
      "fileName": "codechickenlib-1.12.2-3.2.3.358-universal.jar",
      "staged": true,
      "deleted": false,
      "md5": "U9u3WbFdDHk02t3tK72Y0Q==",
      "fileId": 0
    },
    {
      "fileName": "CustomSkinLoader_Forge-14.10a.jar",
      "staged": true,
      "deleted": false,
      "md5": "h3dgCibZwTleBAXIgXE4OA==",
      "fileId": 0
    },
    {
      "fileName": "distinctdamagedescriptions-1.4.2-fix-TCon.jar",
      "staged": true,
      "deleted": false,
      "md5": "+Q3PUT0tZMNcDtfnKiV2Wg==",
      "fileId": 0
    },
    {
      "fileName": "Fix4Log4J-Forge1.12.2-BukkitAny-1.2.3.jar",
      "staged": true,
      "deleted": false,
      "md5": "8xCAl7NwwueCwhIOMppSww==",
      "fileId": 0
    },
    {
      "fileName": "FTBBackups-1.1.0.1.jar",
      "staged": true,
      "deleted": false,
      "md5": "Ke5AddOH9umPmsmLBqjsiw==",
      "fileId": 0
    },
    {
      "fileName": "FTBLib-5.4.7.2.jar",
      "staged": true,
      "deleted": false,
      "md5": "hVcgVO97xMkTs7rrhEAdpg==",
      "fileId": 0
    },
    {
      "fileName": "Hwyla-1.8.26-B41_1.12.2.jar",
      "staged": true,
      "deleted": false,
      "md5": "VOZ2LwyhFvuFkr9GI/JSfA==",
      "fileId": 0
    },
    {
      "fileName": "InputMethodBlocker-1.11-1.12.2-2.2-SNAPSHOT.jar",
      "staged": true,
      "deleted": false,
      "md5": "08hHj0hhqA/N0CkBL5LwCQ==",
      "fileId": 0
    },
    {
      "fileName": "lostcities-1.12-2.0.22.jar",
      "staged": true,
      "deleted": false,
      "md5": "Yc+gJ3cjC0WqrcYccl17Mg==",
      "fileId": 0
    },
    {
      "fileName": "lostcitychest.json",
      "staged": true,
      "deleted": false,
      "md5": "hsdZzv3oU1H0+qms3IPqZw==",
      "fileId": 0
    },
    {
      "fileName": "ModularVoiceChat-1.1-patch.jar",
      "staged": true,
      "deleted": false,
      "md5": "HuyVbIpNLrFv9EpBii0S6g==",
      "fileId": 0
    },
    {
      "fileName": "phosphor-1.12.2-0.2.8-SNAPSHOT-universal (1).jar",
      "staged": true,
      "deleted": false,
      "md5": "+uHy956AnmeREPKpW+XdLw==",
      "fileId": 0
    },
    {
      "fileName": "thegreatsunrising-1.1.0-for1122.jar",
      "staged": true,
      "deleted": false,
      "md5": "mLnqVQ8LBSwgjvWZX2qWtA==",
      "fileId": 0
    }
  ],
  "240967": [
    {
      "fileName": "BaseMetals-1.12-2.5.0-rc2.332.jar",
      "staged": false,
      "deleted": false,
      "md5": "IrL2qzP1aDRvddwsF3xITw==",
      "fileId": 2712965
    }
  ],
  "227083": [
    {
      "fileName": "Baubles-1.12-1.5.2.jar",
      "staged": false,
      "deleted": false,
      "md5": "lE3sTvP7/U1JjZSnBHryAQ==",
      "fileId": 2518667
    }
  ],
  "340583": [
    {
      "fileName": "bettercaves-1.12.2-2.0.4.jar",
      "staged": false,
      "deleted": false,
      "md5": "zrnIirX481FKKK1yRLgXVw==",
      "fileId": 3003242
    }
  ],
  "229876": [
    {
      "fileName": "BetterFps-1.4.8.jar",
      "staged": false,
      "deleted": false,
      "md5": "029NPA+W6ZqaGtLo7tofxA==",
      "fileId": 2483393
    }
  ],
  "390497": [
    {
      "fileName": "BetterHurtTimer-1.12.2-1.5.0.1.jar",
      "staged": false,
      "deleted": false,
      "md5": "DtZVU24FfLyvjV3LMkGpPQ==",
      "fileId": 3168647
    }
  ],
  "389665": [
    {
      "fileName": "BetterMineshaftsForge-1.12.2-2.2.1.jar",
      "staged": false,
      "deleted": false,
      "md5": "Hn83FXghyHIJWkXhN5cA0A==",
      "fileId": 3247154
    }
  ],
  "309110": [
    {
      "fileName": "biggerpacketsplz-since1.8-1.2.jar",
      "staged": false,
      "deleted": false,
      "md5": "nrniT1acwemSJrGnttR3sQ==",
      "fileId": 2655843
    }
  ],
  "255255": [
    {
      "fileName": "birdsfoods-1.12\u002B-\u002B3.1.jar",
      "staged": false,
      "deleted": false,
      "md5": "11ODH/Jqn9K9bm5GGlcwDQ==",
      "fileId": 2517254
    }
  ],
  "269167": [
    {
      "fileName": "BottledMilk-1.12-1.1.0.jar",
      "staged": false,
      "deleted": false,
      "md5": "wB6+MQ+SFzWbcFim96cbMQ==",
      "fileId": 2520532
    }
  ],
  "313536": [
    {
      "fileName": "Bountiful\u002BBaubles-1.12.2-0.1.8.jar",
      "staged": false,
      "deleted": false,
      "md5": "k1ZZ+v+1iOGdCfWgExHukw==",
      "fileId": 3568240
    }
  ],
  "235279": [
    {
      "fileName": "Chisel-MC1.12.2-1.0.2.45.jar",
      "staged": false,
      "deleted": false,
      "md5": "VK/CmPlOcI8OHN85kgCyyw==",
      "fileId": 2915375
    }
  ],
  "342584": [
    {
      "fileName": "collective-1.12.2-3.0.jar",
      "staged": false,
      "deleted": false,
      "md5": "tcqWoBWlj9yK+ilzq+ewsA==",
      "fileId": 3533131
    }
  ],
  "290541": [
    {
      "fileName": "CompatSkills-1.12.2-1.17.0.jar",
      "staged": false,
      "deleted": false,
      "md5": "KUS/liVCeOVNwM+UbxJHAw==",
      "fileId": 2815688
    }
  ],
  "287683": [
    {
      "fileName": "conarm-1.12.2-1.2.5.10.jar",
      "staged": false,
      "deleted": false,
      "md5": "tb8ckxrEebdni+qLhiSsnw==",
      "fileId": 3174535
    }
  ],
  "237749": [
    {
      "fileName": "coroutil-1.12.1-1.2.37.jar",
      "staged": false,
      "deleted": false,
      "md5": "NQwhZ4S7VM/8U4Mlq1LUzA==",
      "fileId": 2902920
    }
  ],
  "239197": [
    {
      "fileName": "CraftTweaker2-1.12-4.1.20.646.jar",
      "staged": false,
      "deleted": false,
      "md5": "XAOLWTb/5ghPzIZr7CX6AQ==",
      "fileId": 3294372
    }
  ],
  "257814": [
    {
      "fileName": "CreativeCore_v1.10.69_mc1.12.2.jar",
      "staged": false,
      "deleted": false,
      "md5": "aTGQvpUhNmiW67q3XQEpTQ==",
      "fileId": 3537907
    }
  ],
  "267602": [
    {
      "fileName": "CTM-MC1.12.2-1.0.2.31.jar",
      "staged": false,
      "deleted": false,
      "md5": "d6i7VIbJfj6qb0XlvXaIZA==",
      "fileId": 2915363
    }
  ],
  "261427": [
    {
      "fileName": "DamageControl-1.12.2-1.3.15.jar",
      "staged": false,
      "deleted": false,
      "md5": "HolihHVRVxN6JN79u6wX1w==",
      "fileId": 2643966
    }
  ],
  "309344": [
    {
      "fileName": "DynamicStealth-1.12.2.114.jar",
      "staged": false,
      "deleted": false,
      "md5": "T31EPx7PJ7gWjm64Q4sfpg==",
      "fileId": 3337921
    }
  ],
  "261605": [
    {
      "fileName": "easiervillagertrading-1.12-forge14.21.1.2387-1.3.jar",
      "staged": false,
      "deleted": false,
      "md5": "CojybpbboGEr9QWaqf9/qg==",
      "fileId": 2656954
    }
  ],
  "442962": [
    {
      "fileName": "ElenaiDodge2-1.12.2-1.1.0.jar",
      "staged": false,
      "deleted": false,
      "md5": "Wt/Xwk5b+r0Mqa6bnKl1HA==",
      "fileId": 3343308
    }
  ],
  "315773": [
    {
      "fileName": "FantasticLib-1.12.2.047.jar",
      "staged": false,
      "deleted": false,
      "md5": "mBeBC85bTBoO3MZbkX+xvA==",
      "fileId": 3341793
    }
  ],
  "296430": [
    {
      "fileName": "foodfunk-1.12.2-4.9.6.jar",
      "staged": false,
      "deleted": false,
      "md5": "RBNf3O3Z/z4/XcBF6IUgLg==",
      "fileId": 2849124
    }
  ],
  "248453": [
    {
      "fileName": "Forgelin-1.8.4.jar",
      "staged": false,
      "deleted": false,
      "md5": "LaefznImXqsFQeVlY204nQ==",
      "fileId": 2785465
    }
  ],
  "280294": [
    {
      "fileName": "FpsReducer-mc1.12.2-1.20.jar",
      "staged": false,
      "deleted": false,
      "md5": "fogEL5Tb/Mup6Dm2QM9ZLg==",
      "fileId": 3362160
    }
  ],
  "237102": [
    {
      "fileName": "FTBUtilities-5.4.1.131.jar",
      "staged": false,
      "deleted": false,
      "md5": "lHdatnXgIEUjyfJnl2tw1Q==",
      "fileId": 3157548
    }
  ],
  "310059": [
    {
      "fileName": "future-mc-0.2.9.jar",
      "staged": false,
      "deleted": false,
      "md5": "3m89QXQjOLTJD5lLt+Tn5w==",
      "fileId": 3722997
    }
  ],
  "76544": [
    {
      "fileName": "GeographiCraft-1.12-0.8.9b.jar",
      "staged": false,
      "deleted": false,
      "md5": "CyFlsFp7OFEnNpHkEmsuTg==",
      "fileId": 2497541
    }
  ],
  "289479": [
    {
      "fileName": "guns-0.15.3-1.12.2.jar",
      "staged": false,
      "deleted": false,
      "md5": "573JHEwXp1vOZ7blI4aTQA==",
      "fileId": 2854400
    }
  ],
  "450270": [
    {
      "fileName": "handoveryouritems_1.12.2-1.2.jar",
      "staged": false,
      "deleted": false,
      "md5": "Nzn4bqgsxDtiIrNcXwAibg==",
      "fileId": 3233170
    }
  ],
  "62786": [
    {
      "fileName": "HideNames-1.12.2-1.4.1.jar",
      "staged": false,
      "deleted": false,
      "md5": "yLilUU8TSnrdL9U+u2APCw==",
      "fileId": 2874509
    }
  ],
  "297209": [
    {
      "fileName": "hooked-1.0.3.jar",
      "staged": false,
      "deleted": false,
      "md5": "qM/NmVPEk03zqNv376vpgg==",
      "fileId": 2607310
    }
  ],
  "224476": [
    {
      "fileName": "HungerOverhaul-1.12.2-1.3.3.jenkins148.jar",
      "staged": false,
      "deleted": false,
      "md5": "YYhChecklcF2nA4Ccwz1kA==",
      "fileId": 2565122
    }
  ],
  "223094": [
    {
      "fileName": "InventoryTweaks-1.64\u002Bdev.146.jar",
      "staged": false,
      "deleted": false,
      "md5": "PF1Cj6ywwL8jHH8U+fy+Dw==",
      "fileId": 2670367
    }
  ],
  "390992": [
    {
      "fileName": "InvMove-1.12.2-0.4.6.jar",
      "staged": false,
      "deleted": false,
      "md5": "QsVYXFwzBHo/E3AmvmG+1w==",
      "fileId": 3023870
    }
  ],
  "238222": [
    {
      "fileName": "jei_1.12.2-4.16.1.302.jar",
      "staged": false,
      "deleted": false,
      "md5": "LcS2BGgS5kxRT/TRi8XLAw==",
      "fileId": 3043174
    }
  ],
  "32274": [
    {
      "fileName": "journeymap-1.12.2-5.7.1.jar",
      "staged": false,
      "deleted": false,
      "md5": "gWC5cPwUz/MN/yeFu5+WTA==",
      "fileId": 2916002
    }
  ],
  "250702": [
    {
      "fileName": "JustEnoughCharacters-1.12.0-3.4.5.jar",
      "staged": false,
      "deleted": false,
      "md5": "zpDacwMUTlJuI5gP9FWqRA==",
      "fileId": 2822814
    }
  ],
  "240630": [
    {
      "fileName": "JustEnoughResources-1.12.2-0.9.2.60.jar",
      "staged": false,
      "deleted": false,
      "md5": "h6RmZUmmDY+0I4g91O5iMg==",
      "fileId": 2728585
    }
  ],
  "252910": [
    {
      "fileName": "librarianlib-1.12.2-4.22.jar",
      "staged": false,
      "deleted": false,
      "md5": "9hTXsXaVdBepNun0HS5/4A==",
      "fileId": 3041340
    }
  ],
  "255257": [
    {
      "fileName": "LootTweaker-0.3.1\u002BMC1.12.2.jar",
      "staged": false,
      "deleted": false,
      "md5": "DXSIbu5+J1YmnoNi4N/TLw==",
      "fileId": 3507866
    }
  ],
  "271998": [
    {
      "fileName": "lostsouls-1.12-1.1.4.jar",
      "staged": false,
      "deleted": false,
      "md5": "YwLmDvN/9aUXzVQ0728Dmg==",
      "fileId": 2533316
    }
  ],
  "74924": [
    {
      "fileName": "Mantle-1.12-1.3.3.55.jar",
      "staged": false,
      "deleted": false,
      "md5": "ECb1+NPEmXgx3s2QI8plpg==",
      "fileId": 2713386
    }
  ],
  "531346": [
    {
      "fileName": "Meds\u002BMod.jar",
      "staged": false,
      "deleted": false,
      "md5": "oyKfqjiEivIILjImrvhYZQ==",
      "fileId": 3472536
    }
  ],
  "226294": [
    {
      "fileName": "MineTweakerRecipeMaker-1.12.2-1.2.2.30.jar",
      "staged": false,
      "deleted": false,
      "md5": "rgp/pNhh9QFASV3pSq+Y9g==",
      "fileId": 2497436
    }
  ],
  "261744": [
    {
      "fileName": "MMDLib-1.12-1.0.0-rc2.36.jar",
      "staged": false,
      "deleted": false,
      "md5": "Gxo/OWrb2aTN1+LC50NJCw==",
      "fileId": 2712947
    }
  ],
  "225738": [
    {
      "fileName": "MmmMmmMmmMmm-1.12-1.14.jar",
      "staged": false,
      "deleted": false,
      "md5": "/LtGVvzZvr5MafTIRwEong==",
      "fileId": 2503041
    }
  ],
  "244357": [
    {
      "fileName": "ModernMetals-1.12-2.5.0-rc2.152.jar",
      "staged": false,
      "deleted": false,
      "md5": "UP9WW/rZ8V5+24hbQgW6mg==",
      "fileId": 2712959
    }
  ],
  "220954": [
    {
      "fileName": "modtweaker-4.0.18.jar",
      "staged": false,
      "deleted": false,
      "md5": "0RfibmtXixjSWEj1eOhsOw==",
      "fileId": 2881277
    }
  ],
  "60089": [
    {
      "fileName": "MouseTweaks-2.10-mc1.12.2.jar",
      "staged": false,
      "deleted": false,
      "md5": "5Ny/R8P5mngGgeOjqfz56Q==",
      "fileId": 2671937
    }
  ],
  "373051": [
    {
      "fileName": "movingelevators-1.3.5-mc1.12.jar",
      "staged": false,
      "deleted": false,
      "md5": "1h+VxZ8HSOeGgs7RGW+F1w==",
      "fileId": 3706405
    }
  ],
  "253211": [
    {
      "fileName": "MTLib-3.0.6.jar",
      "staged": false,
      "deleted": false,
      "md5": "tGdINiwEbXC4IRITMSRqpQ==",
      "fileId": 2684561
    }
  ],
  "227887": [
    {
      "fileName": "MultiMine-1.12.2.jar",
      "staged": false,
      "deleted": false,
      "md5": "NdrHnBhh12ifs2rw2BI20Q==",
      "fileId": 2790649
    }
  ],
  "514409": [
    {
      "fileName": "NoCubes_SRP_Addon_2.3.1.jar",
      "staged": false,
      "deleted": false,
      "md5": "SwzITdWIcbtNAdSpOrfeJg==",
      "fileId": 3541406
    }
  ],
  "256359": [
    {
      "fileName": "NonUpdate-AllMCVersion-Final-2.0.2-universal.jar",
      "staged": false,
      "deleted": false,
      "md5": "OBxqdhDk4tjkyl21KrD6tQ==",
      "fileId": 2656640
    }
  ],
  "558773": [
    {
      "fileName": "Nutrition-1.12.2-4.9.0.jar",
      "staged": false,
      "deleted": false,
      "md5": "0/ugp/4+85I3gZSeK1nAnQ==",
      "fileId": 3574440
    }
  ],
  "349214": [
    {
      "fileName": "Nyx-1.4.2.jar",
      "staged": false,
      "deleted": false,
      "md5": "Fmyzq060zjhMUtfQKSJe8w==",
      "fileId": 3161738
    }
  ],
  "289380": [
    {
      "fileName": "obfuscate-0.2.7-1.12.2.jar",
      "staged": false,
      "deleted": false,
      "md5": "vujpry/y/9W38EcBJ3PXWQ==",
      "fileId": 2906168
    }
  ],
  "245586": [
    {
      "fileName": "OreSpawn-1.12-3.3.1.179.jar",
      "staged": false,
      "deleted": false,
      "md5": "If9xvFqPCzCybH/OFvf+kg==",
      "fileId": 2913786
    }
  ],
  "580404": [
    {
      "fileName": "overlast-1.12.2-0.2.3B4.jar",
      "staged": false,
      "deleted": false,
      "md5": "qcd17zOucS757TcKMKQ8Qw==",
      "fileId": 3755364
    }
  ],
  "314002": [
    {
      "fileName": "overloadedarmorbar-1.0.4g.jar",
      "staged": false,
      "deleted": false,
      "md5": "rK1CHDG6RGWfSAnXZ+Y4IQ==",
      "fileId": 2719400
    }
  ],
  "227951": [
    {
      "fileName": "placeableitems-3.3.jar",
      "staged": false,
      "deleted": false,
      "md5": "FlIe+7ACRZLB8Fd/KEoiPQ==",
      "fileId": 2543705
    }
  ],
  "266890": [
    {
      "fileName": "PlayerRevive_v1.2.40_mc1.12.2.jar",
      "staged": false,
      "deleted": false,
      "md5": "SirxfAc7xD9gdtRVWcZxag==",
      "fileId": 3169485
    }
  ],
  "345779": [
    {
      "fileName": "plonk-1.12.2-5.0.5.jar",
      "staged": false,
      "deleted": false,
      "md5": "+UFpHjHR8yiHb2uIAViy9g==",
      "fileId": 3299037
    }
  ],
  "376903": [
    {
      "fileName": "plustic-8.0.5.jar",
      "staged": false,
      "deleted": false,
      "md5": "xljkNAnd7bxUw6/T6k3y/A==",
      "fileId": 3648592
    }
  ],
  "242872": [
    {
      "fileName": "PotionCore-1.9_for_1.12.2.jar",
      "staged": false,
      "deleted": false,
      "md5": "Xeo5Cy5hlns10j9zrfc7rQ==",
      "fileId": 2905184
    }
  ],
  "444043": [
    {
      "fileName": "preview_OptiFine_1.12.2_HD_U_G6_pre1.jar",
      "staged": false,
      "deleted": false,
      "md5": "nuQQC41DD4yKqC5vOxO4fg==",
      "fileId": 3378442
    }
  ],
  "264756": [
    {
      "fileName": "QualityTools-1.0.7_for_1.12.2.jar",
      "staged": false,
      "deleted": false,
      "md5": "pdsWLOWtFkUdjZYb6ook8A==",
      "fileId": 2732994
    }
  ],
  "243121": [
    {
      "fileName": "Quark-r1.6-179.jar",
      "staged": false,
      "deleted": false,
      "md5": "38+nDSRPBDWl/ysoA3oySw==",
      "fileId": 2924091
    }
  ],
  "285612": [
    {
      "fileName": "randompatches-1.12.2-1.22.1.10.jar",
      "staged": false,
      "deleted": false,
      "md5": "37sw/zluZCa6mihLBMe88w==",
      "fileId": 3133651
    }
  ],
  "606838": [
    {
      "fileName": "replaymod-1.12.2-2.6.4.jar",
      "staged": false,
      "deleted": false,
      "md5": "cOELMag/RZynvTQo6PcA5w==",
      "fileId": 3740296
    }
  ],
  "286382": [
    {
      "fileName": "Reskillable-1.12.2-1.13.0.jar",
      "staged": false,
      "deleted": false,
      "md5": "OOZqCaj1yQJ4r2b9qV0nZA==",
      "fileId": 2815686
    }
  ],
  "226447": [
    {
      "fileName": "ResourceLoader-MC1.12.1-1.5.3.jar",
      "staged": false,
      "deleted": false,
      "md5": "URQeiC+WznVrmz0l8qzfVw==",
      "fileId": 2477566
    }
  ],
  "375840": [
    {
      "fileName": "Roleplay\u002B_1.12.2_1.0.4.jar",
      "staged": false,
      "deleted": false,
      "md5": "NKNa4gDm+I5pyoXi9DwIaw==",
      "fileId": 3196712
    }
  ],
  "313124": [
    {
      "fileName": "SBM-Punt-Animal-1.12.2-1.0.0b20190202141059.jar",
      "staged": false,
      "deleted": false,
      "md5": "BWO3MN+JTRSoVV4O4T8bpw==",
      "fileId": 2668156
    }
  ],
  "327056": [
    {
      "fileName": "smooth-scrolling-everywhere-1.1.jar",
      "staged": false,
      "deleted": false,
      "md5": "AFuWa4XEMZ7X0cWvUs3NwA==",
      "fileId": 2922328
    }
  ],
  "286932": [
    {
      "fileName": "Soviet\u002BEra\u002B0.6.jar",
      "staged": false,
      "deleted": false,
      "md5": "TxE77aicJ8STFeIun3Dgyg==",
      "fileId": 3641414
    }
  ],
  "252239": [
    {
      "fileName": "SpartanShields-1.12.2-1.5.5.jar",
      "staged": false,
      "deleted": false,
      "md5": "55xdzmynoYhxwiG5+I0laA==",
      "fileId": 3567495
    }
  ],
  "284754": [
    {
      "fileName": "SpawnerControl-1.6.3b.jar",
      "staged": false,
      "deleted": false,
      "md5": "GAmSnxPqbRbL8DA2/R5Pfg==",
      "fileId": 2725062
    }
  ],
  "348025": [
    {
      "fileName": "SRParasites-1.12.2v1.9.5.jar",
      "staged": false,
      "deleted": false,
      "md5": "enPZQDiQwlUMJsZpfaf0PQ==",
      "fileId": 3755305
    }
  ],
  "438332": [
    {
      "fileName": "supermartijn642configlib-1.0.9a-mc1.12.jar",
      "staged": false,
      "deleted": false,
      "md5": "iLK8tap4SO4kABHd1lkpTg==",
      "fileId": 3666797
    }
  ],
  "454372": [
    {
      "fileName": "supermartijn642corelib-1.0.16b-mc1.12.jar",
      "staged": false,
      "deleted": false,
      "md5": "ciQGVXXgVq5xv0DPX7Nrpw==",
      "fileId": 3751319
    }
  ],
  "74072": [
    {
      "fileName": "TConstruct-1.12.2-2.13.0.183.jar",
      "staged": false,
      "deleted": false,
      "md5": "cQ1kNC1BBCt9bO2JFEjnJw==",
      "fileId": 2902483
    }
  ],
  "272671": [
    {
      "fileName": "TinkersComplement-1.12.2-0.4.3.jar",
      "staged": false,
      "deleted": false,
      "md5": "kF9lkLM9SzuoDZc/OXnQ0A==",
      "fileId": 2843439
    }
  ],
  "308629": [
    {
      "fileName": "tinkersforging-1.1.4.jar",
      "staged": false,
      "deleted": false,
      "md5": "McM2/jNUM2ZCZcFH1nyh7g==",
      "fileId": 2719685
    }
  ],
  "291786": [
    {
      "fileName": "tinkersjei-1.2.jar",
      "staged": false,
      "deleted": false,
      "md5": "sreUb901J0X3WpZ28N9Row==",
      "fileId": 2701203
    }
  ],
  "545353": [
    {
      "fileName": "TinkersOreDictCache-1.0.jar",
      "staged": false,
      "deleted": false,
      "md5": "tRm3OBW4ZIE3YRWZ/vtArw==",
      "fileId": 3519479
    }
  ],
  "294667": [
    {
      "fileName": "TinkerSurvival-1.12.2-1.2.3.1.jar",
      "staged": false,
      "deleted": false,
      "md5": "rgtVpemCJevj61zYNZewGA==",
      "fileId": 3760594
    }
  ],
  "320903": [
    {
      "fileName": "totaltinkers-0.6.0.jar",
      "staged": false,
      "deleted": false,
      "md5": "aPLGPqaw8xEId8Xe+fcgMg==",
      "fileId": 3243998
    }
  ],
  "313816": [
    {
      "fileName": "toughnessbar-2.4.jar",
      "staged": false,
      "deleted": false,
      "md5": "Em9+tsSHtvsQQH8wHqSHgg==",
      "fileId": 2851670
    }
  ],
  "469262": [
    {
      "fileName": "Trident-1.0.1.jar",
      "staged": false,
      "deleted": false,
      "md5": "Zlu1BN7ShSUaTAdzsjLHJQ==",
      "fileId": 3316385
    }
  ],
  "292785": [
    {
      "fileName": "VanillaFix-1.0.10-150.jar",
      "staged": false,
      "deleted": false,
      "md5": "p0qqtoEA4D9U410QB9UBaQ==",
      "fileId": 2915154
    }
  ],
  "286660": [
    {
      "fileName": "vehicle-mod-0.44.1-1.12.2.jar",
      "staged": false,
      "deleted": false,
      "md5": "J2gYdwZnwb/1adkih8U9lQ==",
      "fileId": 2967287
    }
  ],
  "554861": [
    {
      "fileName": "VillagerTrades-1.12.2-0.6.5.jar",
      "staged": false,
      "deleted": false,
      "md5": "qyyLTfXRcfWY0nwTpfZkaQ==",
      "fileId": 3556724
    }
  ],
  "238048": [
    {
      "fileName": "VTweaks-1.12.2-2.0.8.jar",
      "staged": false,
      "deleted": false,
      "md5": "689nkPHy3BNzlowFo5u4CA==",
      "fileId": 2875136
    }
  ],
  "79287": [
    {
      "fileName": "WailaHarvestability-mc1.12-1.1.12.jar",
      "staged": false,
      "deleted": false,
      "md5": "C9h2X/MGS+M2yxsJII5BDA==",
      "fileId": 2481605
    }
  ],
  "295319": [
    {
      "fileName": "walljump-1.12.2-1.3.2.jar",
      "staged": false,
      "deleted": false,
      "md5": "hFvf90L0T0ICFFjqKJcpHg==",
      "fileId": 2865090
    }
  ],
  "224712": [
    {
      "fileName": "Wawla-1.12.2-2.5.273.jar",
      "staged": false,
      "deleted": false,
      "md5": "/oG3/lN0zi0WQYNqFOvjfw==",
      "fileId": 2707185
    }
  ],
  "257572": [
    {
      "fileName": "WearableBackpacks-1.12.2-3.1.4.jar",
      "staged": false,
      "deleted": false,
      "md5": "69pPqd0a+8RFcUuy6Kiggw==",
      "fileId": 2800372
    }
  ],
  "261019": [
    {
      "fileName": "WorldEdit\u002BCUI\u002BForge\u002BEdition\u002B2-2.1.2-mf-1.12.2-14.23.5.2768.jar",
      "staged": false,
      "deleted": false,
      "md5": "w7cxJtriQSt/IkDbQHPP/Q==",
      "fileId": 2629417
    }
  ],
  "225608": [
    {
      "fileName": "worldedit-forge-mc1.12.2-6.1.10-dist.jar",
      "staged": false,
      "deleted": false,
      "md5": "vfbY0gWRwBT+1mYz9O87Iw==",
      "fileId": 2941712
    }
  ],
  "298323": [
    {
      "fileName": "wumpleutil-1.12.2-2.12.9.jar",
      "staged": false,
      "deleted": false,
      "md5": "VaOc0I1QOnp3HNw+f1xWLQ==",
      "fileId": 2849447
    }
  ],
  "399377": [
    {
      "fileName": "YungsLaw-1.12.2-1.0.4.jar",
      "staged": false,
      "deleted": false,
      "md5": "a4djeZBgOpc91nFPZpYy4w==",
      "fileId": 3113274
    }
  ],
  "237754": [
    {
      "fileName": "zombieawareness-1.12.1-1.11.16.jar",
      "staged": false,
      "deleted": false,
      "md5": "jOGHBGmMJj+/Wc8kdZF6OA==",
      "fileId": 2663393
    }
  ],
  "405327": [
    {
      "fileName": "[___MixinCompat-0.8___].jar",
      "staged": false,
      "deleted": false,
      "md5": "kQOO2YPgqXSJI4llIEZcMQ==",
      "fileId": 3045381
    }
  ],
  "357178": [
    {
      "fileName": "_MixinBootstrap-1.1.0.jar",
      "staged": false,
      "deleted": false,
      "md5": "nfDcYo6814cnD0h/u/gVeg==",
      "fileId": 3437402
    }
  ],
  "271384": [
    {
      "fileName": "CoFHWorld-1.12.2-1.4.0.1-universal.jar",
      "staged": false,
      "deleted": false,
      "md5": "8r/XTna3G97oogqSQ91c3w==",
      "fileId": 2920434
    }
  ]
}